{
    "Воронежская область":  {
                                "Объем патентов и нематериальных активов 2023":  818,
                                "Объем рынка 2022":  1570655,
                                "Рентабельность рынка 2021":  10,
                                "Коэффициент Джини по выручке 2024":  55,
                                "Коэффициент быстрой ликвидности 2023":  122,
                                "Доля убыточных компаний 2023":  20,
                                "Долг/Собственный капитал 2024":  126,
                                "Количество фирм 2021":  12,
                                "Объем инвестиций в основной капитал 2020":  725029,
                                "Средняя доля затрат в выручке 2024":  61,
                                "Средняя доля затрат в выручке 2021":  72,
                                "Долг/EBITDA 2021":  411,
                                "Средняя доля затрат в выручке 2022":  85,
                                "Долг/EBITDA 2022":  185,
                                "Средний срок оборачиваемости активов 2023":  396,
                                "Уровень финансовой нестабильности (индекс Ниши) 2022":  59,
                                "Количество фирм 2020":  11,
                                "Уровень финансовой нестабильности (индекс Ниши) 2021":  22,
                                "Доля компаний, занимающихся НИОКР 2021":  6,
                                "Объем инвестиций в основной капитал 2022":  730174,
                                "Объем патентов и нематериальных активов 2022":  176,
                                "Объем рынка 2023":  9515253,
                                "Объем инвестиций в НИОКР 2021":  4967,
                                "Объем инвестиций в основной капитал 2024":  645099,
                                "Средний срок оборачиваемости активов 2024":  331,
                                "Рентабельность рынка 2022":  12,
                                "Уровень финансовой нестабильности (индекс Ниши) 2020":  31,
                                "Доля компаний с отрицательными чистыми активами 2021":  46,
                                "Доля компаний с отрицательными чистыми активами 2022":  44,
                                "Рентабельность рынка 2020":  9,
                                "Уровень финансовой нестабильности (индекс Ниши) 2024":  52,
                                "Доля убыточных компаний 2021":  45,
                                "Средняя доля затрат в выручке 2020":  63,
                                "Количество фирм 2023":  42,
                                "Коэффициент Джини по выручке 2021":  89,
                                "Долг/Собственный капитал 2021":  103,
                                "Коэффициент Джини по выручке 2022":  65,
                                "Средняя доля затрат в выручке 2023":  81,
                                "Средний срок оборачиваемости активов 2022":  377,
                                "Долг/Собственный капитал 2022":  85,
                                "Доля убыточных компаний 2020":  30,
                                "Объем инвестиций в основной капитал 2023":  221595,
                                "Доля компаний, занимающихся НИОКР 2023":  0,
                                "Доля убыточных компаний 2024":  28,
                                "Объем рынка 2021":  7845859,
                                "Объем патентов и нематериальных активов 2021":  364,
                                "Коэффициент текущей ликвидности 2020":  110,
                                "Объем инвестиций в НИОКР 2023":  754,
                                "Долг/EBITDA 2024":  485,
                                "Объем инвестиций в НИОКР 2024":  9789,
                                "Рентабельность рынка 2024":  19,
                                "Долг/EBITDA 2020":  263,
                                "Объем инвестиций в НИОКР 2020":  6725,
                                "Коэффициент быстрой ликвидности 2020":  65,
                                "Доля убыточных компаний 2022":  30,
                                "Доля компаний, занимающихся НИОКР 2020":  0,
                                "Объем патентов и нематериальных активов 2020":  738,
                                "Коэффициент текущей ликвидности 2023":  122,
                                "Объем инвестиций в основной капитал 2021":  11628,
                                "Долг/EBITDA 2023":  137,
                                "Коэффициент Джини по выручке 2023":  98,
                                "Средняя динамика рынка за 5 лет":  129,
                                "Доля компаний с отрицательными чистыми активами 2024":  29,
                                "Средний срок оборачиваемости активов 2021":  352,
                                "Количество фирм 2024":  33,
                                "Доля компаний с отрицательными чистыми активами 2020":  13,
                                "Долг/Собственный капитал 2023":  139,
                                "Уровень финансовой нестабильности (индекс Ниши) 2023":  36,
                                "Рентабельность рынка 2023":  9,
                                "Объем инвестиций в НИОКР 2022":  9414,
                                "Доля компаний с отрицательными чистыми активами 2023":  38,
                                "Долг/Собственный капитал 2020":  76,
                                "Коэффициент текущей ликвидности 2024":  101,
                                "Коэффициент быстрой ликвидности 2022":  74,
                                "Коэффициент быстрой ликвидности 2021":  118,
                                "Количество фирм 2022":  34,
                                "Объем рынка 2020":  292014,
                                "Доля компаний, занимающихся НИОКР 2024":  0,
                                "Объем патентов и нематериальных активов 2024":  669,
                                "Средний срок оборачиваемости активов 2020":  522,
                                "Коэффициент текущей ликвидности 2022":  176,
                                "Доля компаний, занимающихся НИОКР 2022":  6,
                                "Объем рынка 2024":  9725921,
                                "Коэффициент текущей ликвидности 2021":  135,
                                "Коэффициент быстрой ликвидности 2024":  58,
                                "Коэффициент Джини по выручке 2020":  65
                            }
}